[
    {
        "module": 1,
        "syllabus":"",
        "Noteslink":"",
        "testbooklink":""
    },
    {
        "module": 2,
        "syllabus":"",
        "Noteslink":"",
        "testbooklink":""
    },
    {
        "module": 3,
        "syllabus":"",
        "Noteslink":"",
        "testbooklink":""
    },
    {
        "module": 4,
        "syllabus":"",
        "Noteslink":"",
        "testbooklink":""
    },
    {
        "module": 5,
        "syllabus":"",
        "Noteslink":"",
        "testbooklink":""
    }
]